keyframe/__init__.py
keyframe/scene.py
keyframe-0.0.1.dist-info/METADATA
keyframe-0.0.1.dist-info/WHEEL
keyframe-0.0.1.dist-info/licenses/LICENSE
keyframe-0.0.1.dist-info/RECORD
